figrecipes/__init__.py
figrecipes/plot.py
figrecipes/tests/__init__.py
figrecipes/tests/test_plots.py
figrecipes-0.0.7.dist-info/LICENSE
figrecipes-0.0.7.dist-info/METADATA
figrecipes-0.0.7.dist-info/WHEEL
figrecipes-0.0.7.dist-info/top_level.txt
figrecipes-0.0.7.dist-info/RECORD
