Metadata-Version: 2.1
Name: figrecipes
Version: 0.0.7
Summary: figrecipes is a tool for quickly creating interactive plots for data science.
Home-page: https://github.com/hackingmaterials/figrecipes
Author: Anubhav Jain
Author-email: anubhavster@gmail.com
License: modified BSD
Platform: UNKNOWN
Classifier: Programming Language :: Python :: 2.7
Classifier: Development Status :: 4 - Beta
Classifier: Intended Audience :: Science/Research
Classifier: Intended Audience :: System Administrators
Classifier: Intended Audience :: Information Technology
Classifier: Operating System :: OS Independent
Classifier: Topic :: Other/Nonlisted Topic
Classifier: Topic :: Scientific/Engineering
License-File: LICENSE
Requires-Dist: plotly (>=4.14.3)
Requires-Dist: pandas (>=1.3.0)
Requires-Dist: monty (>=2021.6.10)
Requires-Dist: numpy (>=1.21.0)
Requires-Dist: scipy (>=1.6.3)
Requires-Dist: sphinx
Requires-Dist: invoke (>=1.5.0)
